sonnylabs/__init__.py
sonnylabs/client.py
sonnylabs-0.1.2.dist-info/licenses/LICENSE
sonnylabs-0.1.2.dist-info/METADATA
sonnylabs-0.1.2.dist-info/WHEEL
sonnylabs-0.1.2.dist-info/top_level.txt
sonnylabs-0.1.2.dist-info/RECORD
