Metadata-Version: 2.4
Name: sonnylabs
Version: 0.1.2
Summary: Python client for the SonnyLabs AI Security Scanner - Test your AI applications for prompt injection vulnerabilities
Author-email: SonnyLabs <liana@sonnylabs.ai>
License: MIT
Project-URL: Homepage, https://sonnylabs.ai
Project-URL: Documentation, https://github.com/SonnyLabs/sonnylabs_py#readme
Project-URL: Repository, https://github.com/SonnyLabs/sonnylabs_py
Project-URL: Bug Tracker, https://github.com/SonnyLabs/sonnylabs_py/issues
Keywords: ai,security,prompt injection,vulnerability,scanner,cybersecurity,testing
Classifier: Development Status :: 3 - Alpha
Classifier: Intended Audience :: Developers
Classifier: Topic :: Security
Classifier: Topic :: Software Development :: Testing
Classifier: Topic :: Scientific/Engineering :: Artificial Intelligence
Classifier: Programming Language :: Python :: 3
Classifier: Programming Language :: Python :: 3.7
Classifier: Programming Language :: Python :: 3.8
Classifier: Programming Language :: Python :: 3.9
Classifier: Programming Language :: Python :: 3.10
Classifier: Programming Language :: Python :: 3.11
Classifier: Programming Language :: Python :: 3.12
Classifier: Operating System :: OS Independent
Requires-Python: >=3.7
License-File: LICENSE
Requires-Dist: requests>=2.25.0
Dynamic: license-file
